pkgstruct/__init__.py
pkgstruct/pkgstruct.py
pkgstruct-0.0.2.dist-info/LICENSE
pkgstruct-0.0.2.dist-info/METADATA
pkgstruct-0.0.2.dist-info/WHEEL
pkgstruct-0.0.2.dist-info/top_level.txt
pkgstruct-0.0.2.dist-info/RECORD
