Metadata-Version: 2.2
Name: pkgstruct
Version: 0.0.2
Summary: Utility module for formalising the directory structure of software package
Home-page: https://github.com/nanigashi-uji/pkgstruct.git
Author: Nanigashi Uji
Author-email: 53845049+nanigashi-uji@users.noreply.github.com
License: BSD-3-Clause
Keywords: Directory Structure,GNU Coding Standards,FHS
Classifier: Development Status :: 4 - Beta
Classifier: License :: OSI Approved :: BSD License
Classifier: Programming Language :: Python
Classifier: Programming Language :: Python :: 3
Classifier: Topic :: Software Development :: Libraries :: Python Modules
Classifier: Topic :: System :: Software Distribution
Classifier: Topic :: Utilities
License-File: LICENSE
Dynamic: author
Dynamic: author-email
Dynamic: classifier
Dynamic: description
Dynamic: home-page
Dynamic: keywords
Dynamic: license
Dynamic: summary
